gdpr/__init__.py
gdpr/encryption.py
gdpr/enums.py
gdpr/fields.py
gdpr/ipcypher.py
gdpr/loading.py
gdpr/mixins.py
gdpr/models.py
gdpr/utils.py
gdpr/version.py
gdpr/anonymizers/__init__.py
gdpr/anonymizers/base.py
gdpr/anonymizers/fields.py
gdpr/anonymizers/generic_relation.py
gdpr/anonymizers/gis.py
gdpr/anonymizers/hash_fields.py
gdpr/anonymizers/model_anonymizers.py
gdpr/anonymizers/local/__init__.py
gdpr/anonymizers/local/cs.py
gdpr/locale/cs/LC_MESSAGES/django.mo
gdpr/locale/cs/LC_MESSAGES/django.po
gdpr/management/__init__.py
gdpr/management/commands/__init__.py
gdpr/management/commands/anonymize_data.py
gdpr/management/commands/deactivate_expired_reasons.py
gdpr/migrations/0001_initial.py
gdpr/migrations/0002_auto_20180509_1518.py
gdpr/migrations/0003.py
gdpr/migrations/0004.py
gdpr/migrations/0005_anon_2_0.py
gdpr/migrations/0006_auto_20190228_0725.py
gdpr/migrations/0007_migration.py
gdpr/migrations/0008_migration.py
gdpr/migrations/0009_migration.py
gdpr/migrations/0010_migration.py
gdpr/migrations/0011_migration.py
gdpr/migrations/__init__.py
gdpr/purposes/__init__.py
gdpr/purposes/default.py
gdpr/tests/__init__.py
gdpr/tests/test_cs_fields.py
gdpr/tests/test_encryption.py
gdpr/tests/test_fields.py
gdpr/tests/test_gis_fields.py
gdpr/tests/test_ipcypher.py
skip_django_gdpr-0.6.1.dist-info/licenses/LICENSE
tests/__init__.py
tests/anonymizers.py
tests/models.py
tests/purposes.py
tests/test_settings.py
tests/validators.py
tests/migrations/0001_initial.py
tests/migrations/0002_note.py
tests/migrations/0003_IBAN.py
tests/migrations/0004_facebook_id.py
tests/migrations/0005_avatar.py
tests/migrations/0006_auto_20190305_0323.py
tests/migrations/0007_childe_extraparentd_parentb_parentc_topparenta.py
tests/migrations/0008_customerregistration.py
tests/migrations/__init__.py
tests/tests/__init__.py
tests/tests/data.py
tests/tests/test_deactivate_expired_reasons.py
tests/tests/test_empty.py
tests/tests/test_fields.py
tests/tests/test_legal_reason.py
tests/tests/test_model_anonymization.py
tests/tests/utils.py
skip_django_gdpr-0.6.1.dist-info/METADATA
skip_django_gdpr-0.6.1.dist-info/WHEEL
skip_django_gdpr-0.6.1.dist-info/top_level.txt
skip_django_gdpr-0.6.1.dist-info/RECORD
