Metadata-Version: 2.4
Name: skip-django-GDPR
Version: 0.6.1
Summary: Library for GDPR implementation
Home-page: https://github.com/skip-pay/django-GDPR
Author: Druids
Author-email: matllubos@gmail.com
License: MIT
Classifier: Development Status :: 3 - Alpha
Classifier: Framework :: Django
Classifier: Framework :: Django :: 1.10
Classifier: Framework :: Django :: 1.11
Classifier: Framework :: Django :: 2.0
Classifier: Framework :: Django :: 2.1
Classifier: Intended Audience :: Developers
Classifier: License :: OSI Approved :: MIT License
Classifier: Operating System :: OS Independent
Classifier: Programming Language :: Python
Classifier: Programming Language :: Python :: 3.6
Classifier: Programming Language :: Python :: 3.7
Classifier: Programming Language :: Python :: 3 :: Only
Classifier: Intended Audience :: Developers
Classifier: Topic :: Internet :: WWW/HTTP :: Dynamic Content
License-File: LICENSE
Requires-Dist: django>=4.2
Requires-Dist: skip-django-chamber>=0.7.2
Requires-Dist: tqdm>=4.28.1
Requires-Dist: pyaes>=1.6.1
Requires-Dist: unidecode
Requires-Dist: skip-django-choice-enumfields>=1.1.3.2
Dynamic: author
Dynamic: author-email
Dynamic: classifier
Dynamic: description
Dynamic: description-content-type
Dynamic: home-page
Dynamic: license
Dynamic: license-file
Dynamic: requires-dist
Dynamic: summary
